README.txt
setup.py
src/ClearWrap.egg-info/PKG-INFO
src/ClearWrap.egg-info/SOURCES.txt
src/ClearWrap.egg-info/dependency_links.txt
src/ClearWrap.egg-info/requires.txt
src/ClearWrap.egg-info/top_level.txt
src/clearwrap/__init__.py
src/clearwrap/clearparser.py