Metadata-Version: 1.0
Name: ClearWrap
Version: 0.2
Summary: Wrapper for ClearParser
Home-page: https://bitbucket.org/nicta_biomed/clearwrap
Author: Andy MacKinlay
Author-email: andrew.mackinlay@nicta.com.au 
License: Apache 2.0
Platform: UNKNOWN
